odoo/addons/base_maintenance/README.rst
odoo/addons/base_maintenance/__init__.py
odoo/addons/base_maintenance/__manifest__.py
odoo/addons/base_maintenance/i18n/base_maintenance.pot
odoo/addons/base_maintenance/i18n/es.po
odoo/addons/base_maintenance/i18n/it.po
odoo/addons/base_maintenance/i18n/pt_BR.po
odoo/addons/base_maintenance/models/__init__.py
odoo/addons/base_maintenance/models/maintenance_team.py
odoo/addons/base_maintenance/readme/CONTRIBUTORS.rst
odoo/addons/base_maintenance/readme/DESCRIPTION.rst
odoo/addons/base_maintenance/static/description/icon.png
odoo/addons/base_maintenance/static/description/index.html
odoo/addons/base_maintenance/views/maintenance_equipment_views.xml
odoo/addons/base_maintenance/views/maintenance_request_views.xml
odoo/addons/base_maintenance/views/maintenance_team_views.xml
odoo/addons/base_maintenance/views/report_maintenance_request.xml
odoo13_addon_base_maintenance-13.0.1.2.0.dist-info/METADATA
odoo13_addon_base_maintenance-13.0.1.2.0.dist-info/WHEEL
odoo13_addon_base_maintenance-13.0.1.2.0.dist-info/top_level.txt
odoo13_addon_base_maintenance-13.0.1.2.0.dist-info/RECORD
